plugin_gifsicle/__init__.py
plugin_gifsicle/gifsicle_binaries/arm/gifsicle
plugin_gifsicle/gifsicle_binaries/x86/gifsicle
plugin_gifsicle-0.3.1.dist-info/LICENSE.txt
plugin_gifsicle-0.3.1.dist-info/METADATA
plugin_gifsicle-0.3.1.dist-info/WHEEL
plugin_gifsicle-0.3.1.dist-info/top_level.txt
plugin_gifsicle-0.3.1.dist-info/RECORD
