Metadata-Version: 2.1
Name: plugin_gifsicle
Version: 0.3.1
Summary: Gifiscle binaries to both x86 and ARM for Indigo Plugin (and others!)
Author: GlennNZ
Author-email: GlennNZ <Try_Forum@IndigoDomo.com>
Maintainer-email: GlennNZ <See_Forum@Indigodomo.com>
License: MIT License
Project-URL: Homepage, https://github.com/Ghawken/plugin_gifiscle
Project-URL: Bug Reports, https://github.com/Ghawken/plugin_gifiscle
Project-URL: Funding, https://donate.pypi.org
Project-URL: Say Thanks!, https://github.com/Ghawken/plugin_gifiscle
Project-URL: Source, https://github.com/Ghawken/plugin_gifiscle
Classifier: Development Status :: 4 - Beta
Classifier: Intended Audience :: Developers
Classifier: Topic :: Software Development :: Build Tools
Classifier: Programming Language :: Python :: 3.11
Classifier: Programming Language :: Python :: 3 :: Only
Requires-Python: >=3.10
License-File: LICENSE.txt
